{
  "name": "Bloodbath Blades",
  "system": {
    "category": {
      "value": "incantation"
    },
    "description": {
      "value": "<p>Summons countless magical spinning blades that slash through the air. All characters and all monsters take damage equal to [INT + SPI]. The caster alone is unaffected by this spell.</p>"
    },
    "spell": {
      "activation": {
        "cast": "normal",
        "mental": 10
      },
      "duration": {
        "value": 1,
        "type": "instant",
        "custom": ""
      },
      "level": "high",
      "range": {
        "value": "caster"
      },
      "target": {
        "custom": "All areas"
      }
    },
    "source": {
      "book": "Ryuutama",
      "custom": ""
    },
    "actions": {
      "damage": {
        "formula": "@stats.intelligence + @stats.spirit",
        "properties": []
      },
      "healing": {
        "formula": "",
        "properties": []
      }
    },
    "identifier": "bloodbath-blades"
  },
  "_id": "bloodbathblades0",
  "type": "spell",
  "img": "icons/sundries/books/book-embossed-clasp-gold-brown.webp",
  "effects": [],
  "folder": "incantationhigh0",
  "sort": 0,
  "ownership": {
    "default": 0
  },
  "flags": {},
  "_stats": {
    "compendiumSource": null,
    "duplicateSource": null,
    "exportSource": null,
    "coreVersion": "14.357",
    "systemId": "ryuutama",
    "systemVersion": "2.0.0",
    "createdTime": 1774638906427,
    "modifiedTime": null,
    "lastModifiedBy": "ryuutama00000000"
  },
  "_key": "!items!bloodbathblades0"
}
