{
  "_id": "travelinggear000",
  "name": "Traveling Gear",
  "type": "Item",
  "description": "",
  "folder": null,
  "sorting": "a",
  "sort": 0,
  "color": "#855614",
  "flags": {},
  "_stats": {
    "compendiumSource": null,
    "duplicateSource": null,
    "exportSource": null,
    "coreVersion": "13.350",
    "systemId": "ryuutama",
    "systemVersion": "DEVELOP",
    "createdTime": 1759688655814,
    "modifiedTime": null,
    "lastModifiedBy": "ryuutama00000000"
  },
  "_key": "!folders!travelinggear000"
}
