{
  "name": "Well-Spoken",
  "_id": "wellspoken000000",
  "type": "skill",
  "system": {
    "description": {
      "value": "<p>As a merchant who earns her keep by trading, your communication skills are top notch.</p><p><strong>Skill Effect:</strong> Negotiation Check [INT + SPI] gets +1, always in effect</p><p><strong>Usable Circumstances:</strong> Any Negotiation Check</p><p><strong>Stat Used:</strong> -</p><p><strong>TN:</strong> -</p>"
    },
    "identifier": "well-spoken",
    "source": {
      "book": "Ryuutama",
      "custom": ""
    }
  },
  "img": "icons/skills/social/diplomacy-handshake-yellow.webp",
  "effects": [],
  "folder": "merchant00000000",
  "sort": 0,
  "ownership": {
    "default": 0
  },
  "flags": {},
  "_stats": {
    "compendiumSource": null,
    "duplicateSource": null,
    "exportSource": null,
    "coreVersion": "14.357",
    "systemId": "ryuutama",
    "systemVersion": "2.0.0",
    "createdTime": 1774638708686,
    "modifiedTime": null,
    "lastModifiedBy": "ryuutama00000000"
  },
  "_key": "!items!wellspoken000000"
}
